eazy_square.py
eazy_square-0.1.0.dist-info/WHEEL
eazy_square-0.1.0.dist-info/METADATA
eazy_square-0.1.0.dist-info/RECORD
