Metadata-Version: 2.1
Name: eazy-square
Version: 0.1.0
Summary: Square(w, h).draw(size)
Author: fab4key
Requires-Python: >=3.7,<4.0
Classifier: Programming Language :: Python :: 3
Classifier: Programming Language :: Python :: 3.7
Classifier: Programming Language :: Python :: 3.8
Classifier: Programming Language :: Python :: 3.9
